CHANGELOG.rst
CONTRIBUTORS.rst
LICENSE.txt
stochastic/__init__.py
stochastic/_version.py
stochastic/base.py
stochastic/continuous/__init__.py
stochastic/continuous/bessel.py
stochastic/continuous/brownian_bridge.py
stochastic/continuous/brownian_excursion.py
stochastic/continuous/brownian_meander.py
stochastic/continuous/brownian_motion.py
stochastic/continuous/cauchy.py
stochastic/continuous/fractional_brownian_motion.py
stochastic/continuous/gamma.py
stochastic/continuous/geometric_brownian_motion.py
stochastic/continuous/inverse_gaussian.py
stochastic/continuous/mixed_poisson.py
stochastic/continuous/multifractional_brownian_motion.py
stochastic/continuous/poisson.py
stochastic/continuous/squared_bessel.py
stochastic/continuous/variance_gamma.py
stochastic/continuous/wiener.py
stochastic/diffusion/__init__.py
stochastic/diffusion/constant_elasticity_variance.py
stochastic/diffusion/cox_ingersoll_ross.py
stochastic/diffusion/ornstein_uhlenbeck.py
stochastic/diffusion/vasicek.py
stochastic/discrete/__init__.py
stochastic/discrete/bernoulli.py
stochastic/discrete/chinese_restaurant.py
stochastic/discrete/markov_chain.py
stochastic/discrete/moran.py
stochastic/discrete/random_walk.py
stochastic/noise/__init__.py
stochastic/noise/colored_noise.py
stochastic/noise/fractional_gaussian_noise.py
stochastic/noise/gaussian_noise.py
stochastic-0.5.0.dist-info/LICENSE.txt
stochastic-0.5.0.dist-info/WHEEL
stochastic-0.5.0.dist-info/METADATA
stochastic-0.5.0.dist-info/RECORD
