Metadata-Version: 2.1
Name: stochastic
Version: 0.5.0
Summary: Generate realizations of stochastic processes
Home-page: https://github.com/crflynn/stochastic
License: MIT
Keywords: stochastic,processes
Author: Flynn
Author-email: crf204@gmail.com
Requires-Python: >=3.6,<4.0
Classifier: Development Status :: 3 - Alpha
Classifier: Intended Audience :: Science/Research
Classifier: License :: OSI Approved :: MIT License
Classifier: Natural Language :: English
Classifier: Programming Language :: Python :: 3
Classifier: Programming Language :: Python :: 3.6
Classifier: Programming Language :: Python :: 3.7
Classifier: Programming Language :: Python :: 3.8
Classifier: Programming Language :: Python :: Implementation :: CPython
Classifier: Topic :: Scientific/Engineering
Classifier: Topic :: Scientific/Engineering :: Mathematics
Classifier: Topic :: Scientific/Engineering :: Physics
Requires-Dist: numpy (>=1.17,<2.0)
Requires-Dist: scipy (>=1.3,<2.0)
Project-URL: Documentation, https://stochastic.readthedocs.io/en/latest/
Project-URL: Repository, https://github.com/crflynn/stochastic
